grpc_pytools/__init__.py
grpc_pytools/digest.py
grpc_pytools/digest_generator.py
grpc_pytools/generator.py
grpc_pytools/gohttp.py
grpc_pytools/helpers.py
grpc_pytools/marshmallow.py
grpc_pytools/pi.py
grpc_pytools/pythonic.py
grpc_pytools/restart.py
grpc_pytools/protoc_plugins/__init__.py
grpc_pytools/protoc_plugins/ast.py
grpc_pytools/protoc_plugins/generator.py
grpc_pytools-0.1.3.dist-info/DESCRIPTION.rst
grpc_pytools-0.1.3.dist-info/METADATA
grpc_pytools-0.1.3.dist-info/RECORD
grpc_pytools-0.1.3.dist-info/WHEEL
grpc_pytools-0.1.3.dist-info/entry_points.txt
grpc_pytools-0.1.3.dist-info/metadata.json
grpc_pytools-0.1.3.dist-info/top_level.txt
