Metadata-Version: 2.0
Name: grpc-pytools
Version: 0.1.3
Summary: Some useful Python's gRPC tools.
Home-page: https://github.com/RussellLuo/grpc-pytools
Author: RussellLuo
Author-email: luopeng.he@gmail.com
License: MIT
Keywords: gRPC,Python tools
Platform: UNKNOWN
Requires-Dist: grpcio
Requires-Dist: marshmallow
Requires-Dist: python-restart
